imei_lookup/__init__.py
imei_lookup/main.py
imei_lookup-0.1.0.dist-info/METADATA
imei_lookup-0.1.0.dist-info/WHEEL
imei_lookup-0.1.0.dist-info/top_level.txt
imei_lookup-0.1.0.dist-info/RECORD
