Metadata-Version: 2.1
Name: imei-lookup
Version: 0.1.0
Summary: A library for looking up IMEI information
